django_yeouia-2.0.0.dist-info/METADATA
django_yeouia-2.0.0.dist-info/RECORD
django_yeouia-2.0.0.dist-info/WHEEL
django_yeouia-2.0.0.dist-info/top_level.txt
yeouia/__init__.py
yeouia/apps.py
yeouia/backends.py
yeouia/tests.py
