Metadata-Version: 2.1
Name: django-yeouia
Version: 2.0.0
Summary: A Django auth backend that works with email or username
Home-page: https://github.com/nim65s/django-YummyEmailOrUsernameInsensitiveAuth
Author: Guilhem Saurel
Author-email: webmaster@saurel.me
License: BSD
Platform: UNKNOWN
Classifier: Environment :: Web Environment
Classifier: Framework :: Django
Classifier: Intended Audience :: Developers
Classifier: License :: OSI Approved :: BSD License
Classifier: Operating System :: OS Independent
Classifier: Programming Language :: Python
Classifier: Programming Language :: Python :: 3.4
Classifier: Programming Language :: Python :: 3.5
Classifier: Programming Language :: Python :: 3.6
Classifier: Programming Language :: Python :: 3.7
Classifier: Topic :: Internet :: WWW/HTTP
Classifier: Topic :: Internet :: WWW/HTTP :: Dynamic Content
Requires-Python: >=3.4
